trame/__init__.py
trame/modules/__init__.py
trame/modules/remote_control.py
trame/widgets/__init__.py
trame/widgets/remote_control.py
trame_remote_control/__init__.py
trame_remote_control/actions/__init__.py
trame_remote_control/actions/catalyst.py
trame_remote_control/actions/paraview_server.py
trame_remote_control/modules/__init__.py
trame_remote_control/modules/remote_control.py
trame_remote_control/widgets/__init__.py
trame_remote_control/widgets/remote_control.py
trame_remote_control-0.1.1.dist-info/LICENSE
trame_remote_control-0.1.1.dist-info/METADATA
trame_remote_control-0.1.1.dist-info/WHEEL
trame_remote_control-0.1.1.dist-info/top_level.txt
trame_remote_control-0.1.1.dist-info/RECORD
