Metadata-Version: 2.1
Name: trame-remote-control
Version: 0.1.1
Summary: A trame extension to allow outside programs to send instructions to a trame app
Author-email: Jonathan Windgassen <j.windgassen@fz-juelich.de>
License: MIT License
Project-URL: Repository, https://github.com/jwindgassen/trame-remote-control
Project-URL: Issues, https://github.com/jwindgassen/trame-remote-control/issues
Keywords: Python,Interactive,Web,Application,Framework,ParaView,trame
Classifier: Development Status :: 4 - Beta
Classifier: Environment :: Web Environment
Classifier: License :: OSI Approved :: MIT License
Classifier: Natural Language :: English
Classifier: Operating System :: OS Independent
Classifier: Programming Language :: Python :: 3
Classifier: Programming Language :: Python :: 3 :: Only
Classifier: Programming Language :: Python :: 3.9
Classifier: Programming Language :: Python :: 3.10
Classifier: Programming Language :: Python :: 3.11
Classifier: Programming Language :: Python :: 3.12
Classifier: Topic :: Scientific/Engineering :: Visualization
Classifier: Topic :: Software Development :: Libraries :: Application Frameworks
Classifier: Topic :: Software Development :: Libraries :: Python Modules
Requires-Python: >=3.9
License-File: LICENSE
Requires-Dist: trame
Requires-Dist: trame-vuetify
Requires-Dist: aiohttp
